ecv_data_access/__init__.py
ecv_data_access/actris.py
ecv_data_access/argo.py
ecv_data_access/exv.py
ecv_data_access/functions.py
ecv_data_access/iagos.py
ecv_data_access/icos.py
ecv_data_access/json_cache.py
ecv_data_access/misc.py
ecv_data_access/seadatanet.py
tests/test_functions.py
ecv_data_access-0.1.10.dist-info/METADATA
ecv_data_access-0.1.10.dist-info/WHEEL
ecv_data_access-0.1.10.dist-info/top_level.txt
ecv_data_access-0.1.10.dist-info/RECORD
