Metadata-Version: 2.4
Name: ecv-data-access
Version: 0.1.10
Summary: This package is a proof of concept for accessing data across multiple scientific disciplines. The requests are structured around the ECV (Essential Variable) vocabulary: [https://vocab.nerc.ac.uk/collection/EXV/current/](https://vocab.nerc.ac.uk/collection/EXV/current/). The package was developed during the EnvriHub Next hackathon in Amsterdam and is funded by the EnvriHub Next (EHN) project.
Project-URL: Homepage, https://gitlab.a.incd.pt/envri-hub-next/ecv-data-access
Requires-Python: >=3.7
Requires-Dist: pandas
Requires-Dist: requests
Requires-Dist: jupyter
Requires-Dist: shapely
Requires-Dist: matplotlib
Requires-Dist: pillow
Requires-Dist: argopy
Requires-Dist: numpy
Requires-Dist: cartopy
Requires-Dist: SPARQLWrapper
Requires-Dist: erddapy
Requires-Dist: pyarrow
Requires-Dist: icoscp_core==0.3.10
